{
"type": "FeatureCollection",
"name": "change_local_tr",
"crs": { "type": "name", "properties": { "name": "urn:ogc:def:crs:OGC:1.3:CRS84" } },
"features": [
{ "type": "Feature", "properties": { "fid": 4, "NAME": "TR" }, "geometry": { "type": "Point", "coordinates": [ 30.284051748719811, 59.900586860684761 ] } },
{ "type": "Feature", "properties": { "fid": 5, "NAME": "TR" }, "geometry": { "type": "Point", "coordinates": [ 30.283660803305665, 59.900441187213076 ] } }
]
}
