{
"type": "FeatureCollection",
"name": "kick-scooter_parking",
"crs": { "type": "name", "properties": { "name": "urn:ogc:def:crs:OGC:1.3:CRS84" } },
"features": [
{ "type": "Feature", "properties": { "full_id": "n12203686870", "osm_id": "12203686870", "osm_type": "node", "amenity": "kick-scooter_parking" }, "geometry": { "type": "Point", "coordinates": [ 30.4100211, 59.8327635 ] } }
]
}
