{
"type": "FeatureCollection",
"name": "traffic_park",
"crs": { "type": "name", "properties": { "name": "urn:ogc:def:crs:OGC:1.3:CRS84" } },
"features": [
{ "type": "Feature", "properties": { "fid": 1, "amenity": "traffic_park" }, "geometry": { "type": "Point", "coordinates": [ 30.480158532206001, 59.882596065157514 ] } }
]
}
